newsletter_signup/__init__.py
newsletter_signup/admin.py
newsletter_signup/forms.py
newsletter_signup/middleware.py
newsletter_signup/models.py
newsletter_signup/settings.py
newsletter_signup/urls.py
newsletter_signup/views.py
newsletter_signup/management/__init__.py
newsletter_signup/management/commands/__init__.py
newsletter_signup/management/commands/check_newsletter_signups.py
newsletter_signup/migrations/0001_initial.py
newsletter_signup/migrations/0002_auto_20160412_0430.py
newsletter_signup/migrations/0003_auto_20161207_0341.py
newsletter_signup/migrations/__init__.py
newsletter_signup/templates/newsletter_signup/signup.html
newsletter_signup/templates/newsletter_signup/unsubscribe.html
newsletter_signup/templates/newsletter_signup/verify.html
newsletter_signup/templates/newsletter_signup/ajax/signup.html
newsletter_signup/templates/newsletter_signup/email/subscribe_body.html
newsletter_signup/templates/newsletter_signup/email/subscribe_subject.html
newsletter_signup/templates/newsletter_signup/email/unsubscribe_body.html
newsletter_signup/templates/newsletter_signup/email/unsubscribe_subject.html
newsletter_signup/templates/newsletter_signup/partials/signup_form.html
newsletter_signup/templatetags/__init__.py
newsletter_signup/templatetags/newsletter_signup.py
newsletter_signup/tests/__init__.py
newsletter_signup/tests/forms_tests.py
newsletter_signup/tests/management_tests.py
newsletter_signup/tests/middleware_tests.py
newsletter_signup/tests/models_tests.py
newsletter_signup/tests/newsletter_signup_tags_tests.py
newsletter_signup/tests/settings.py
newsletter_signup/tests/test_settings.py
newsletter_signup/tests/urls.py
newsletter_signup/tests/views_tests.py
django_newsletter_signup-0.7.5.dist-info/AUTHORS
django_newsletter_signup-0.7.5.dist-info/LICENSE
django_newsletter_signup-0.7.5.dist-info/METADATA
django_newsletter_signup-0.7.5.dist-info/WHEEL
django_newsletter_signup-0.7.5.dist-info/top_level.txt
django_newsletter_signup-0.7.5.dist-info/RECORD
