Metadata-Version: 2.1
Name: django-newsletter-signup
Version: 0.7.5
Summary: A reusable Django app, that handles newsletter subscriptions
Home-page: https://github.com/bitmazk/django-newsletter-signup
Author: Daniel Kaufhold
Author-email: daniel.kaufhold@bitmazk.com
License: The MIT License
Keywords: django,app,reusable,newsletter,signup,subscription,email
Platform: OS Independent
License-File: LICENSE
License-File: AUTHORS
Requires-Dist: Django
Requires-Dist: django-libs
Requires-Dist: six
Provides-Extra: dev
Requires-Dist: django-libs (>=1.67.2) ; extra == 'dev'
Requires-Dist: flake8 ; extra == 'dev'
Requires-Dist: django-nose ; extra == 'dev'
Requires-Dist: coverage ; extra == 'dev'
Requires-Dist: django-coverage ; extra == 'dev'
Requires-Dist: ipdb ; extra == 'dev'
Requires-Dist: fabric3 ; extra == 'dev'
Requires-Dist: mixer ; extra == 'dev'
Requires-Dist: mock ; extra == 'dev'
Requires-Dist: tox ; extra == 'dev'
